bin/__init__.py
bin/main.py
spysecli/__init__.py
spysecli/client.py
spysecli/input_parser.py
spysecli/printer.py
spysecli-0.1.6.dist-info/LICENSE.md
spysecli-0.1.6.dist-info/METADATA
spysecli-0.1.6.dist-info/WHEEL
spysecli-0.1.6.dist-info/entry_points.txt
spysecli-0.1.6.dist-info/top_level.txt
spysecli-0.1.6.dist-info/RECORD
