Metadata-Version: 2.1
Name: spysecli
Version: 0.1.6
Summary: CLI for spyse.com
Home-page: https://github.com/spyse-com/spyse-cli
Author: Roman Romanov
Author-email: roman.romanov@spyse.com
License: MIT License        
Platform: UNKNOWN
License-File: LICENSE.md
Requires-Dist: spyse-python (~=2.2.3)
Requires-Dist: loguru (~=0.5.3)
Requires-Dist: validators (~=0.18.2)
Requires-Dist: click (~=8.0.1)
